attotree/__init__.py
attotree/attotree.py
attotree/increment_version.py
attotree/version.py
attotree-0.1.6.dist-info/LICENSE.txt
attotree-0.1.6.dist-info/METADATA
attotree-0.1.6.dist-info/WHEEL
attotree-0.1.6.dist-info/entry_points.txt
attotree-0.1.6.dist-info/top_level.txt
attotree-0.1.6.dist-info/RECORD
