Metadata-Version: 2.1
Name: attotree
Version: 0.1.6
Summary: description
Home-page: https://github.com/karel-brinda/attotree
Author: Karel Brinda
Author-email: karel.brinda@inria.fr
License: MIT
Classifier: Development Status :: 4 - Beta
Classifier: Programming Language :: Python :: 3 :: Only
Classifier: Operating System :: Unix
Classifier: Environment :: Console
Classifier: License :: OSI Approved :: MIT License
Classifier: Intended Audience :: Science/Research
Classifier: Topic :: Scientific/Engineering :: Bio-Informatics
License-File: LICENSE.txt
Requires-Dist: wheel
